Workbook

Sheet Original Dataset
A1: customer_id | B1: customer_name | C1: customer_type | D1: geography | E1: product_type | F1: channel | G1: expected_monthly_txn_count | H1: expected_monthly_txn_amount_usd | I1: source_of_funds | J1: adverse_media_flag | K1: pep_flag | L1: sanctions_flag | M1: ownership_complexity | N1: baseline_risk | O1: priority_review
A2: C301 | B2: North Peak Retail | C2: Retail | D2: Domestic | E2: Standard checking | F2: Digital | G2: 22 | H2: 8500 | I2: Salary | J2: 0 | K2: 0 | L2: 0 | M2: Low | N2: Low | O2: Annual
A3: C302 | B3: Arbor Holdings LLC | C3: Business | D3: Cross-border | E3: Wire / treasury | F3: Digital | G3: 48 | H3: 124000 | I3: Operating revenue | J3: 1 | K3: 0 | L3: 0 | M3: High | N3: High | O3: Quarterly
A4: C303 | B4: Blue Stone Imports | C4: Business | D4: Cross-border | E4: Wires / cash deposits | F4: Branch + digital | G4: 60 | H4: 210000 | I4: Trade receipts | J4: 0 | K4: 1 | L4: 0 | M4: Medium | N4: High | O4: Quarterly
A5: C304 | B5: Canyon Family Trust | C5: Private wealth | D5: Domestic | E5: Investments / wires | F5: Relationship manager | G5: 16 | H5: 98000 | I5: Wealth / investments | J5: 0 | K5: 0 | L5: 0 | M5: Medium | N5: Medium | O5: Semiannual
A6: C305 | B6: Delta Care Services | C6: Business | D6: Domestic | E6: Payroll / ACH | F6: Branch + digital | G6: 34 | H6: 41000 | I6: Service revenue | J6: 0 | K6: 0 | L6: 0 | M6: Low | N6: Medium | O6: Semiannual
A7: C306 | B7: Evergreen Trading Co | C7: Business | D7: Cross-border | E7: Wires / cash deposits | F7: Digital | G7: 72 | H7: 260000 | I7: Trade receipts | J7: 1 | K7: 0 | L7: 0 | M7: High | N7: High | O7: Quarterly

Sheet Weights
A1: factor | B1: weight_set_a | C1: weight_set_b
A2: customer_type | B2: 0.2 | C2: 0.1
A3: geography | B3: 0.15 | C3: 0.25
A4: product_type | B4: 0.15 | C4: 0.1
A5: channel | B5: 0.1 | C5: 0.05
A6: source_of_funds | B6: 0.1 | C6: 0.1
A7: ownership_complexity | B7: 0.1 | C7: 0.1
A8: adverse_media | B8: 0.1 | C8: 0.15
A9: pep | B9: 0.05 | C9: 0.1
A10: sanctions | B10: 0.05 | C10: 0.05

Sheet Exercise 2
A1: customer_id | B1: customer_name | C1: customer_type | D1: geography | E1: product_type | F1: channel | G1: expected_monthly_txn_count | H1: expected_monthly_txn_amount_usd | I1: source_of_funds | J1: adverse_media_flag | K1: pep_flag | L1: sanctions_flag | M1: ownership_complexity | N1: baseline_risk | O1: priority_review | P1: score_weights_a | Q1: tier_weights_a | R1: score_weights_b | S1: tier_weights_b | T1: tier_changed
A2: C301 | B2: North Peak Retail | C2: Retail | D2: Domestic | E2: Standard checking | F2: Digital | G2: 22 | H2: 8500 | I2: Salary | J2: 0 | K2: 0 | L2: 0 | M2: Low | N2: Low | O2: Annual | P2: =ROUND(0.2*IF('Original Dataset'!C2="Retail",1,IF('Original Dataset'!C2="Business",2,3))+0.15*IF('Original Dataset'!D2="Domestic",1,3)+0.15*IF(OR(ISNUMBER(SEARCH("Standard",'Original Dataset'!E2)),ISNUMBER(SEARCH("Payroll",'Original Dataset'!E2))),1,IF(ISNUMBER(SEARCH("Investments",'Original Dataset'!E2)),2,3))+0.1*IF(AND('Original Dataset'!F2="Digital",'Original Dataset'!C2="Retail"),1,IF(ISNUMBER(SEARCH("Branch",'Original Dataset'!F2)),2,3))+0.1*IF(OR('Original Dataset'!I2="Salary",'Original Dataset'!I2="Service revenue",'Original Dataset'!I2="Operating revenue"),1,IF('Original Dataset'!I2="Wealth / investments",2,3))+0.1*IF('Original Dataset'!M2="Low",1,IF('Original Dataset'!M2="Medium",2,3))+0.1*IF('Original Dataset'!J2=1,3,0)+0.05*IF('Original Dataset'!K2=1,3,0)+0.05*IF('Original Dataset'!L2=1,5,0),2) -> 0.8 | Q2: =IF(P2<1.75,"Low",IF(P2<2.5,"Medium","High")) -> Low | R2: =ROUND(0.1*IF('Original Dataset'!C2="Retail",1,IF('Original Dataset'!C2="Business",2,3))+0.25*IF('Original Dataset'!D2="Domestic",1,3)+0.1*IF(OR(ISNUMBER(SEARCH("Standard",'Original Dataset'!E2)),ISNUMBER(SEARCH("Payroll",'Original Dataset'!E2))),1,IF(ISNUMBER(SEARCH("Investments",'Original Dataset'!E2)),2,3))+0.05*IF(AND('Original Dataset'!F2="Digital",'Original Dataset'!C2="Retail"),1,IF(ISNUMBER(SEARCH("Branch",'Original Dataset'!F2)),2,3))+0.1*IF(OR('Original Dataset'!I2="Salary",'Original Dataset'!I2="Service revenue",'Original Dataset'!I2="Operating revenue"),1,IF('Original Dataset'!I2="Wealth / investments",2,3))+0.1*IF('Original Dataset'!M2="Low",1,IF('Original Dataset'!M2="Medium",2,3))+0.15*IF('Original Dataset'!J2=1,3,0)+0.1*IF('Original Dataset'!K2=1,3,0)+0.05*IF('Original Dataset'!L2=1,5,0),2) -> 0.7 | S2: =IF(R2<1.75,"Low",IF(R2<2.5,"Medium","High")) -> Low | T2: =Q2&" → "&S2 -> Low → Low
A3: C302 | B3: Arbor Holdings LLC | C3: Business | D3: Cross-border | E3: Wire / treasury | F3: Digital | G3: 48 | H3: 124000 | I3: Operating revenue | J3: 1 | K3: 0 | L3: 0 | M3: High | N3: High | O3: Quarterly | P3: =ROUND(0.2*IF('Original Dataset'!C3="Retail",1,IF('Original Dataset'!C3="Business",2,3))+0.15*IF('Original Dataset'!D3="Domestic",1,3)+0.15*IF(OR(ISNUMBER(SEARCH("Standard",'Original Dataset'!E3)),ISNUMBER(SEARCH("Payroll",'Original Dataset'!E3))),1,IF(ISNUMBER(SEARCH("Investments",'Original Dataset'!E3)),2,3))+0.1*IF(AND('Original Dataset'!F3="Digital",'Original Dataset'!C3="Retail"),1,IF(ISNUMBER(SEARCH("Branch",'Original Dataset'!F3)),2,3))+0.1*IF(OR('Original Dataset'!I3="Salary",'Original Dataset'!I3="Service revenue",'Original Dataset'!I3="Operating revenue"),1,IF('Original Dataset'!I3="Wealth / investments",2,3))+0.1*IF('Original Dataset'!M3="Low",1,IF('Original Dataset'!M3="Medium",2,3))+0.1*IF('Original Dataset'!J3=1,3,0)+0.05*IF('Original Dataset'!K3=1,3,0)+0.05*IF('Original Dataset'!L3=1,5,0),2) -> 2.3 | Q3: =IF(P3<1.75,"Low",IF(P3<2.5,"Medium","High")) -> Medium | R3: =ROUND(0.1*IF('Original Dataset'!C3="Retail",1,IF('Original Dataset'!C3="Business",2,3))+0.25*IF('Original Dataset'!D3="Domestic",1,3)+0.1*IF(OR(ISNUMBER(SEARCH("Standard",'Original Dataset'!E3)),ISNUMBER(SEARCH("Payroll",'Original Dataset'!E3))),1,IF(ISNUMBER(SEARCH("Investments",'Original Dataset'!E3)),2,3))+0.05*IF(AND('Original Dataset'!F3="Digital",'Original Dataset'!C3="Retail"),1,IF(ISNUMBER(SEARCH("Branch",'Original Dataset'!F3)),2,3))+0.1*IF(OR('Original Dataset'!I3="Salary",'Original Dataset'!I3="Service revenue",'Original Dataset'!I3="Operating revenue"),1,IF('Original Dataset'!I3="Wealth / investments",2,3))+0.1*IF('Original Dataset'!M3="Low",1,IF('Original Dataset'!M3="Medium",2,3))+0.15*IF('Original Dataset'!J3=1,3,0)+0.1*IF('Original Dataset'!K3=1,3,0)+0.05*IF('Original Dataset'!L3=1,5,0),2) -> 2.25 | S3: =IF(R3<1.75,"Low",IF(R3<2.5,"Medium","High")) -> Medium | T3: =Q3&" → "&S3 -> Medium → Medium
A4: C303 | B4: Blue Stone Imports | C4: Business | D4: Cross-border | E4: Wires / cash deposits | F4: Branch + digital | G4: 60 | H4: 210000 | I4: Trade receipts | J4: 0 | K4: 1 | L4: 0 | M4: Medium | N4: High | O4: Quarterly | P4: =ROUND(0.2*IF('Original Dataset'!C4="Retail",1,IF('Original Dataset'!C4="Business",2,3))+0.15*IF('Original Dataset'!D4="Domestic",1,3)+0.15*IF(OR(ISNUMBER(SEARCH("Standard",'Original Dataset'!E4)),ISNUMBER(SEARCH("Payroll",'Original Dataset'!E4))),1,IF(ISNUMBER(SEARCH("Investments",'Original Dataset'!E4)),2,3))+0.1*IF(AND('Original Dataset'!F4="Digital",'Original Dataset'!C4="Retail"),1,IF(ISNUMBER(SEARCH("Branch",'Original Dataset'!F4)),2,3))+0.1*IF(OR('Original Dataset'!I4="Salary",'Original Dataset'!I4="Service revenue",'Original Dataset'!I4="Operating revenue"),1,IF('Original Dataset'!I4="Wealth / investments",2,3))+0.1*IF('Original Dataset'!M4="Low",1,IF('Original Dataset'!M4="Medium",2,3))+0.1*IF('Original Dataset'!J4=1,3,0)+0.05*IF('Original Dataset'!K4=1,3,0)+0.05*IF('Original Dataset'!L4=1,5,0),2) -> 2.15 | Q4: =IF(P4<1.75,"Low",IF(P4<2.5,"Medium","High")) -> Medium | R4: =ROUND(0.1*IF('Original Dataset'!C4="Retail",1,IF('Original Dataset'!C4="Business",2,3))+0.25*IF('Original Dataset'!D4="Domestic",1,3)+0.1*IF(OR(ISNUMBER(SEARCH("Standard",'Original Dataset'!E4)),ISNUMBER(SEARCH("Payroll",'Original Dataset'!E4))),1,IF(ISNUMBER(SEARCH("Investments",'Original Dataset'!E4)),2,3))+0.05*IF(AND('Original Dataset'!F4="Digital",'Original Dataset'!C4="Retail"),1,IF(ISNUMBER(SEARCH("Branch",'Original Dataset'!F4)),2,3))+0.1*IF(OR('Original Dataset'!I4="Salary",'Original Dataset'!I4="Service revenue",'Original Dataset'!I4="Operating revenue"),1,IF('Original Dataset'!I4="Wealth / investments",2,3))+0.1*IF('Original Dataset'!M4="Low",1,IF('Original Dataset'!M4="Medium",2,3))+0.15*IF('Original Dataset'!J4=1,3,0)+0.1*IF('Original Dataset'!K4=1,3,0)+0.05*IF('Original Dataset'!L4=1,5,0),2) -> 2.15 | S4: =IF(R4<1.75,"Low",IF(R4<2.5,"Medium","High")) -> Medium | T4: =Q4&" → "&S4 -> Medium → Medium
A5: C304 | B5: Canyon Family Trust | C5: Private wealth | D5: Domestic | E5: Investments / wires | F5: Relationship manager | G5: 16 | H5: 98000 | I5: Wealth / investments | J5: 0 | K5: 0 | L5: 0 | M5: Medium | N5: Medium | O5: Semiannual | P5: =ROUND(0.2*IF('Original Dataset'!C5="Retail",1,IF('Original Dataset'!C5="Business",2,3))+0.15*IF('Original Dataset'!D5="Domestic",1,3)+0.15*IF(OR(ISNUMBER(SEARCH("Standard",'Original Dataset'!E5)),ISNUMBER(SEARCH("Payroll",'Original Dataset'!E5))),1,IF(ISNUMBER(SEARCH("Investments",'Original Dataset'!E5)),2,3))+0.1*IF(AND('Original Dataset'!F5="Digital",'Original Dataset'!C5="Retail"),1,IF(ISNUMBER(SEARCH("Branch",'Original Dataset'!F5)),2,3))+0.1*IF(OR('Original Dataset'!I5="Salary",'Original Dataset'!I5="Service revenue",'Original Dataset'!I5="Operating revenue"),1,IF('Original Dataset'!I5="Wealth / investments",2,3))+0.1*IF('Original Dataset'!M5="Low",1,IF('Original Dataset'!M5="Medium",2,3))+0.1*IF('Original Dataset'!J5=1,3,0)+0.05*IF('Original Dataset'!K5=1,3,0)+0.05*IF('Original Dataset'!L5=1,5,0),2) -> 1.75 | Q5: =IF(P5<1.75,"Low",IF(P5<2.5,"Medium","High")) -> Medium | R5: =ROUND(0.1*IF('Original Dataset'!C5="Retail",1,IF('Original Dataset'!C5="Business",2,3))+0.25*IF('Original Dataset'!D5="Domestic",1,3)+0.1*IF(OR(ISNUMBER(SEARCH("Standard",'Original Dataset'!E5)),ISNUMBER(SEARCH("Payroll",'Original Dataset'!E5))),1,IF(ISNUMBER(SEARCH("Investments",'Original Dataset'!E5)),2,3))+0.05*IF(AND('Original Dataset'!F5="Digital",'Original Dataset'!C5="Retail"),1,IF(ISNUMBER(SEARCH("Branch",'Original Dataset'!F5)),2,3))+0.1*IF(OR('Original Dataset'!I5="Salary",'Original Dataset'!I5="Service revenue",'Original Dataset'!I5="Operating revenue"),1,IF('Original Dataset'!I5="Wealth / investments",2,3))+0.1*IF('Original Dataset'!M5="Low",1,IF('Original Dataset'!M5="Medium",2,3))+0.15*IF('Original Dataset'!J5=1,3,0)+0.1*IF('Original Dataset'!K5=1,3,0)+0.05*IF('Original Dataset'!L5=1,5,0),2) -> 1.3 | S5: =IF(R5<1.75,"Low",IF(R5<2.5,"Medium","High")) -> Low | T5: =Q5&" → "&S5 -> Medium → Low
A6: C305 | B6: Delta Care Services | C6: Business | D6: Domestic | E6: Payroll / ACH | F6: Branch + digital | G6: 34 | H6: 41000 | I6: Service revenue | J6: 0 | K6: 0 | L6: 0 | M6: Low | N6: Medium | O6: Semiannual | P6: =ROUND(0.2*IF('Original Dataset'!C6="Retail",1,IF('Original Dataset'!C6="Business",2,3))+0.15*IF('Original Dataset'!D6="Domestic",1,3)+0.15*IF(OR(ISNUMBER(SEARCH("Standard",'Original Dataset'!E6)),ISNUMBER(SEARCH("Payroll",'Original Dataset'!E6))),1,IF(ISNUMBER(SEARCH("Investments",'Original Dataset'!E6)),2,3))+0.1*IF(AND('Original Dataset'!F6="Digital",'Original Dataset'!C6="Retail"),1,IF(ISNUMBER(SEARCH("Branch",'Original Dataset'!F6)),2,3))+0.1*IF(OR('Original Dataset'!I6="Salary",'Original Dataset'!I6="Service revenue",'Original Dataset'!I6="Operating revenue"),1,IF('Original Dataset'!I6="Wealth / investments",2,3))+0.1*IF('Original Dataset'!M6="Low",1,IF('Original Dataset'!M6="Medium",2,3))+0.1*IF('Original Dataset'!J6=1,3,0)+0.05*IF('Original Dataset'!K6=1,3,0)+0.05*IF('Original Dataset'!L6=1,5,0),2) -> 1.1 | Q6: =IF(P6<1.75,"Low",IF(P6<2.5,"Medium","High")) -> Low | R6: =ROUND(0.1*IF('Original Dataset'!C6="Retail",1,IF('Original Dataset'!C6="Business",2,3))+0.25*IF('Original Dataset'!D6="Domestic",1,3)+0.1*IF(OR(ISNUMBER(SEARCH("Standard",'Original Dataset'!E6)),ISNUMBER(SEARCH("Payroll",'Original Dataset'!E6))),1,IF(ISNUMBER(SEARCH("Investments",'Original Dataset'!E6)),2,3))+0.05*IF(AND('Original Dataset'!F6="Digital",'Original Dataset'!C6="Retail"),1,IF(ISNUMBER(SEARCH("Branch",'Original Dataset'!F6)),2,3))+0.1*IF(OR('Original Dataset'!I6="Salary",'Original Dataset'!I6="Service revenue",'Original Dataset'!I6="Operating revenue"),1,IF('Original Dataset'!I6="Wealth / investments",2,3))+0.1*IF('Original Dataset'!M6="Low",1,IF('Original Dataset'!M6="Medium",2,3))+0.15*IF('Original Dataset'!J6=1,3,0)+0.1*IF('Original Dataset'!K6=1,3,0)+0.05*IF('Original Dataset'!L6=1,5,0),2) -> 0.85 | S6: =IF(R6<1.75,"Low",IF(R6<2.5,"Medium","High")) -> Low | T6: =Q6&" → "&S6 -> Low → Low
A7: C306 | B7: Evergreen Trading Co | C7: Business | D7: Cross-border | E7: Wires / cash deposits | F7: Digital | G7: 72 | H7: 260000 | I7: Trade receipts | J7: 1 | K7: 0 | L7: 0 | M7: High | N7: High | O7: Quarterly | P7: =ROUND(0.2*IF('Original Dataset'!C7="Retail",1,IF('Original Dataset'!C7="Business",2,3))+0.15*IF('Original Dataset'!D7="Domestic",1,3)+0.15*IF(OR(ISNUMBER(SEARCH("Standard",'Original Dataset'!E7)),ISNUMBER(SEARCH("Payroll",'Original Dataset'!E7))),1,IF(ISNUMBER(SEARCH("Investments",'Original Dataset'!E7)),2,3))+0.1*IF(AND('Original Dataset'!F7="Digital",'Original Dataset'!C7="Retail"),1,IF(ISNUMBER(SEARCH("Branch",'Original Dataset'!F7)),2,3))+0.1*IF(OR('Original Dataset'!I7="Salary",'Original Dataset'!I7="Service revenue",'Original Dataset'!I7="Operating revenue"),1,IF('Original Dataset'!I7="Wealth / investments",2,3))+0.1*IF('Original Dataset'!M7="Low",1,IF('Original Dataset'!M7="Medium",2,3))+0.1*IF('Original Dataset'!J7=1,3,0)+0.05*IF('Original Dataset'!K7=1,3,0)+0.05*IF('Original Dataset'!L7=1,5,0),2) -> 2.5 | Q7: =IF(P7<1.75,"Low",IF(P7<2.5,"Medium","High")) -> High | R7: =ROUND(0.1*IF('Original Dataset'!C7="Retail",1,IF('Original Dataset'!C7="Business",2,3))+0.25*IF('Original Dataset'!D7="Domestic",1,3)+0.1*IF(OR(ISNUMBER(SEARCH("Standard",'Original Dataset'!E7)),ISNUMBER(SEARCH("Payroll",'Original Dataset'!E7))),1,IF(ISNUMBER(SEARCH("Investments",'Original Dataset'!E7)),2,3))+0.05*IF(AND('Original Dataset'!F7="Digital",'Original Dataset'!C7="Retail"),1,IF(ISNUMBER(SEARCH("Branch",'Original Dataset'!F7)),2,3))+0.1*IF(OR('Original Dataset'!I7="Salary",'Original Dataset'!I7="Service revenue",'Original Dataset'!I7="Operating revenue"),1,IF('Original Dataset'!I7="Wealth / investments",2,3))+0.1*IF('Original Dataset'!M7="Low",1,IF('Original Dataset'!M7="Medium",2,3))+0.15*IF('Original Dataset'!J7=1,3,0)+0.1*IF('Original Dataset'!K7=1,3,0)+0.05*IF('Original Dataset'!L7=1,5,0),2) -> 2.45 | S7: =IF(R7<1.75,"Low",IF(R7<2.5,"Medium","High")) -> Medium | T7: =Q7&" → "&S7 -> High → Medium
